{
  "name": "PancakeSwap Default List",
  "timestamp": "2021-05-06T00:00:00Z",
  "version": {
    "major": 3,
    "minor": 0,
    "patch": 0
  },
  "tags": {},
  "logoURI": "https://tidaldex.com/logo.png",
  "keywords": ["pancake", "default"],
  "tokens": [
    {
      "name": "WBNB Token",
      "symbol": "WBNB",
      "address": "0xbb4cdb9cbd36b01bd1cbaebf2de08d9173bc095c",
      "chainId": 56,
      "decimals": 18,
      "logoURI": "https://tidaldex.com/images/tokens/0xbb4cdb9cbd36b01bd1cbaebf2de08d9173bc095c.png"
    },
    
    
    {
      "name": "Tether USD",
      "symbol": "USDT",
      "address": "0x55d398326f99059fF775485246999027B3197955",
      "chainId": 56,
      "decimals": 18,
      "logoURI": "https://tidaldex.com/images/tokens/0x55d398326f99059ff775485246999027b3197955.png"
    },
    
	{
      "name": "CZBlue",
      "symbol": "CZB",
      "address": "0xd963b2236d227a0302e19f2f9595f424950dc186",
      "chainId": 56,
      "decimals": 18,
      "logoURI": "https://tidaldex.com/images/tokens/0xd963b2236d227a0302e19f2f9595f424950dc186.png"
    },
	{
      "name": "CZUSD",
      "symbol": "CZUSD",
      "address": "0xe68b79e51bf826534ff37aa9cee71a3842ee9c70",
      "chainId": 56,
      "decimals": 18,
      "logoURI": "https://tidaldex.com/images/tokens/0xe68b79e51bf826534ff37aa9cee71a3842ee9c70.png"
    }

	
	
	
	
	
  ]
}
